{
    "1-7-2013": {
        "tier": "Wifi UU",
        "settings": {}
    },
    "2-7-2013": {
        "tier": "Challenge Cup",
        "settings": {
            "gen": "RSE"
        }
    },
    "3-7-2013": {
        "tier": "Random Battle",
        "settings": {}
    },
    "4-7-2013": {
        "tier": "HGSS OU",
        "settings": {}
    },
    "5-7-2013": {
        "tier": "Monotype",
        "settings": {}
    },
    "6-7-2013": {
        "tier": "Wifi OU",
        "settings": {}
    },
    "7-7-2013": {
        "tier": "No Preview Ubers",
        "settings": {}
    },
    "8-7-2013": {
        "tier": "Wifi LU",
        "settings": {}
    },
    "9-7-2013": {
        "tier": "Monogen",
        "settings": {}
    },
    "10-7-2013": {
        "tier": "Wifi NU",
        "settings": {}
    },
    "11-7-2013": {
        "tier": "RBY OU",
        "settings": {}
    },
    "12-7-2013": {
        "tier": "Wifi OU Doubles",
        "settings": {}
    },
    "13-7-2013": {
        "tier": "Battle Factory 6v6",
        "settings": {}
    },
    "14-7-2013": {
        "tier": "Wifi Ubers",
        "settings": {}
    },
    "15-7-2013": {
        "tier": "Wifi LC",
        "settings": {}
    },
    "16-7-2013": {
        "tier": "Challenge Cup",
        "settings": {
            "gen": "HGSS"
        }
    },
    "17-7-2013": {
        "tier": "Wifi UU",
        "settings": {}
    },
    "18-7-2013": {
        "tier": "Wifi Triples",
        "settings": {}
    },
    "19-7-2013": {
        "tier": "Monocolour",
        "settings": {}
    },
    "20-7-2013": {
        "tier": "Wifi OU",
        "settings": {}
    },
    "21-7-2013": {
        "tier": "VGC 2013",
        "settings": {}
    },
    "22-7-2013": {
        "tier": "Wifi NEU",
        "settings": {}
    },
    "23-7-2013": {
        "tier": "Adv OU",
        "settings": {}
    },
    "24-7-2013": {
        "tier": "Wifi LU",
        "settings": {}
    },
    "25-7-2013": {
        "tier": "No Preview OU",
        "settings": {}
    },
    "26-7-2013": {
        "tier": "Wifi Ubers",
        "settings": {}
    },
    "27-7-2013": {
        "tier": "Monotype",
        "settings": {}
    },
    "28-7-2013": {
        "tier": "Battle Factory",
        "settings": {}
    },
    "29-7-2013": {
        "tier": "Wifi OU",
        "settings": {}
    },
    "30-7-2013": {
        "tier": "Challenge Cup",
        "settings": {}
    },
    "31-7-2013": {
        "tier": "Wifi NU",
        "settings": {}
    },
    "30-6-2013": {
        "tier": "Wifi OU",
        "settings": {}
    }
}