{
	"1-6-2018": {"tier": "SM PU", "settings": {}},
	"2-6-2018": {"tier": "SM OU", "settings": {}},
	"3-6-2018": {"tier": "Monogen", "settings": {}},
	"4-6-2018": {"tier": "Challenge Cup", "settings": {}},
	"5-6-2018": {"tier": "SM LU", "settings": {}},
	"6-6-2018": {"tier": "SM Ubers", "settings": {}},
	"7-6-2018": {"tier": "BW2 OU", "settings": {}},
	"8-6-2018": {"tier": "SM NU", "settings": {}},
	"9-6-2018": {"tier": "SM OU", "settings": {}},
	"10-6-2018": {"tier": "Monotype", "settings": {}},
	"11-6-2018": {"tier": "Inverted Challenge Cup", "settings": {}},
	"12-6-2018": {"tier": "SM LC", "settings": {}},
	"13-6-2018": {"tier": "SM UU", "settings": {}},
	"14-6-2018": {"tier": "HGSS OU", "settings": {}},
	"15-6-2018": {"tier": "Middle Cup", "settings": {}},
	"16-6-2018": {"tier": "Battle Factory 6v6", "settings": {}},
	"17-6-2018": {"tier": "SM PU", "settings": {}},
	"18-6-2018": {"tier": "Hackmons Challenge Cup", "settings": {}},
	"19-6-2018": {"tier": "SM LU", "settings": {}},
	"20-6-2018": {"tier": "SM Ubers", "settings": {}},
	"21-6-2018": {"tier": "Monogen", "settings": {}},
	"22-6-2018": {"tier": "SM NU", "settings": {}},
	"23-6-2018": {"tier": "SM OU", "settings": {}},
	"24-6-2018": {"tier": "Monotype", "settings": {}},
	"25-6-2018": {"tier": "RBY OU", "settings": {}},
	"26-6-2018": {"tier": "SM LC", "settings": {}},
	"27-6-2018": {"tier": "Inverted Battle", "settings": {}},
	"28-6-2018": {"tier": "SM UU", "settings": {}},
	"29-6-2018": {"tier": "Battle Factory 6v6", "settings": {}},
	"30-6-2018": {"tier": "SM OU", "settings": {}}
}
